sendwave/pants_docker/__init__.py
sendwave/pants_docker/docker_component.py
sendwave/pants_docker/package.py
sendwave/pants_docker/python_requirement.py
sendwave/pants_docker/register.py
sendwave/pants_docker/sources.py
sendwave/pants_docker/subsystem.py
sendwave/pants_docker/target.py
sendwave/pants_docker/utils.py
sendwave_pants_docker-1.1.2.dist-info/METADATA
sendwave_pants_docker-1.1.2.dist-info/WHEEL
sendwave_pants_docker-1.1.2.dist-info/namespace_packages.txt
sendwave_pants_docker-1.1.2.dist-info/top_level.txt
sendwave_pants_docker-1.1.2.dist-info/RECORD
